{
  "gradeLevel": 3,
  "subject": "رياضيات",
  "subjectEn": "Mathematics",
  "sourcePages": "73-78",
  "domains": [
    {
      "nameAr": "الأعداد والعمليات",
      "nameEn": "Numbers & Operations",
      "standards": [
        {
          "nameAr": "الأعداد الكلية",
          "nameEn": "Whole Numbers",
          "axis": "الأعداد والعد",
          "learningOutcomes": [
            {
              "outcomeAr": "يقرأ الأعداد الكلية ضمن 9999 ويكتبها بالرموز والكلمات",
              "indicators": [
                "يقرأ الأعداد حتى 9999 بالرموز",
                "يقرأ الأعداد حتى 9999 بالكلمات",
                "يكتب الأعداد حتى 9999 بالرموز",
                "يكتب عدداً من أربع منازل ممثلاً بالنماذج",
                "يكتب الأعداد حتى 9999 بالكلمات",
                "يكتب الأعداد حتى 9999 بالطريقة التحليلية",
                "يمثّل عدداً كلياً ضمن أربع منازل بالمحسوس",
                "يميّز منازل الآحاد والعشرات والمئات والألوف في عدد مكوّن من أربع منازل",
                "يقرأ الأرقام الهندية ضمن الـ100",
                "يكتب الأرقام الهندية ضمن الـ100"
              ]
            },
            {
              "outcomeAr": "يعدّ تسلسلياً وقفزياً",
              "indicators": [
                "يعدّ قفزياً (اثنينات، أو خمسات، أو عشرات، أو مئات، أو ألوف) ضمن أربع منازل"
              ]
            }
          ]
        },
        {
          "nameAr": "القيمة المنزلية",
          "nameEn": "Place Value",
          "axis": "العمليات والعلاقات",
          "learningOutcomes": [
            {
              "outcomeAr": "يجد القيمة المنزلية لرقم في عدد ضمن أربع منازل",
              "indicators": [
                "يحدّد رقم كل من الآحاد والعشرات والمئات والألوف في عدد كلي من أربع منازل",
                "يحدّد القيمة المنزلية لرقم في عدد مُعطى ضمن أربع منازل",
                "يستخدم القيمة المنزلية في كتابة العدد بالصورة التحليلية"
              ]
            }
          ]
        },
        {
          "nameAr": "المقارنة والترتيب",
          "nameEn": "Comparison & Ordering",
          "axis": "العمليات والعلاقات",
          "learningOutcomes": [
            {
              "outcomeAr": "يكتب الأعداد بالصورة التحليلية ويوظفها في المقارنات",
              "indicators": [
                "يقارن بين عددين كل منهما مكوّن من أربع منازل على الأكثر",
                "يرتّب أعداداً ضمن أربع منازل تصاعدياً",
                "يرتّب أعداداً ضمن أربع منازل تنازلياً"
              ]
            }
          ]
        },
        {
          "nameAr": "التقريب والتقدير",
          "nameEn": "Rounding & Estimation",
          "axis": "العمليات والعلاقات",
          "learningOutcomes": [
            {
              "outcomeAr": "يقرّب الأعداد الكلية من أربع منازل",
              "indicators": [
                "يقرّب أعداداً كلية من أربع منازل لأقرب عشرة",
                "يقرّب أعداداً كلية من أربع منازل لأقرب مئة",
                "يقرّب أعداداً كلية من أربع منازل لأقرب ألف",
                "يجد أعداداً يحقق تقريبها شروطاً محددة"
              ]
            }
          ]
        },
        {
          "nameAr": "الجمع والطرح",
          "nameEn": "Addition & Subtraction",
          "axis": "العمليات والعلاقات",
          "learningOutcomes": [
            {
              "outcomeAr": "يوظّف التقريب لتقدير نواتج العمليات وإيجادها، والتحقق من صحة إجاباته",
              "indicators": [
                "يقدّر ناتج جمع عددين كليين كل منهما مكوّن من أربع منازل على الأكثر",
                "يقدّر ناتج طرح عددين كليين كل منهما مكوّن من أربع منازل على الأكثر",
                "يوظّف التقريب لتقدير نواتج العمليات",
                "يوظّف التقريب للتحقق من صحة الحل"
              ]
            },
            {
              "outcomeAr": "يجمع ويطرح أعداداً كلية ضمن أربع منازل باستراتيجيات متنوعة",
              "indicators": [
                "يجمع عدداً قريباً من مضاعفات الـ100 إلى عدد مكوّن من أربع منازل",
                "يجد ذهنياً ناتج جمع عدد من مضاعفات 10 وعدد مكوّن من أربع منازل ضمن 9999",
                "يجد ذهنياً ناتج جمع عدد من مضاعفات 100 وعدد مكوّن من أربع منازل ضمن 9999",
                "يجد ذهنياً ناتج جمع عدد من مضاعفات 1000 مع عدد من أربع منازل ضمن 9999",
                "يجمع عددين كل منهما مكوّن من ثلاث منازل مع إعادة تجميع المئات",
                "يجمع عددين كل منهما مكوّن من أربع منازل مع إعادة التجميع",
                "يطرح ذهنياً عددين قريبين من مضاعفات 100 و1000 باستعمال طريقة التجسير",
                "يطرح عددين كل منهما مكوّن من أربع منازل مع إعادة التجميع",
                "يطرح عددين كل منهما مكوّن من أربع منازل أحدهما يحتوي أصفاراً"
              ]
            },
            {
              "outcomeAr": "يحل مسائل تتضمن أعداداً كلية ضمن أربع منازل",
              "indicators": [
                "يحل مسائل رياضية وحياتية من خطوتين على الأكثر تتضمن جمع أعداد من أربع منازل",
                "يحل مسائل حياتية من خطوتين على الأكثر تتضمن جمع أعداد من أربع منازل وطرحها",
                "يحل جملاً مفتوحة على الجمع ضمن أربع منازل",
                "يحل جملاً مفتوحة على الطرح ضمن أربع منازل",
                "يحدّد ما إذا كان المطلوب في المسألة الحياتية الجواب الدقيق أم التقديري"
              ]
            }
          ]
        },
        {
          "nameAr": "الضرب والقسمة",
          "nameEn": "Multiplication & Division",
          "axis": "العمليات والعلاقات",
          "learningOutcomes": [
            {
              "outcomeAr": "يتعرّف حقائق الضرب والقسمة، ويدرك العلاقة بين القسمة والضرب، ويستخدمها في الحسابات",
              "indicators": [
                "يجد ناتج ضرب عدد في 2 ضمن حقائق الضرب الأساسية (حتى 10×10)",
                "يجد ناتج ضرب عدد في 5 ضمن حقائق الضرب الأساسية (حتى 10×10)",
                "يجد ناتج ضرب عدد في 10 ضمن حقائق الضرب الأساسية (حتى 10×10)",
                "يجد ناتج ضرب عدد في 3 ضمن حقائق الضرب الأساسية (حتى 10×10)",
                "يجد ذهنياً ناتج ضرب عدد في 4 بمضاعفة ناتج ضربه في 2",
                "يجد ذهنياً ناتج ضرب عدد في 6 بمضاعفة ناتج ضربه في 3",
                "يجد ناتج ضرب عدد في 9 بضربه في 10 أولاً ثم طرح العدد نفسه",
                "يجد ذهنياً ناتج ضرب عدد في 7 باستعمال حقائق الضرب في 2 و5",
                "يجد ذهنياً ناتج ضرب عدد في 8 بمضاعفة ناتج ضربه في 4",
                "يمثّل عملية الضرب بأكثر من طريقة (العدّ القفزي، رسم صورة)",
                "يكتب جملة الضرب لنموذج مكوّن من مجموعات ثنائية",
                "يكتب جملة الضرب لنموذج مكوّن من مجموعات خماسية",
                "يكتب جملة الضرب لنموذج مكوّن من مجموعات ثلاثية",
                "يكتب جملة الضرب لنموذج مكوّن من مجموعات فيها 10 عناصر",
                "يكمل حقيقة الضرب وحقيقة القسمة المرتبطة بها",
                "يكتب عائلات حقائق الضرب والقسمة المترابطة",
                "يجد ضعف عدد ذهنياً",
                "يذكر العلاقة بين حقائق الضرب للأعداد (2، 4، 8)، (5، 10)، (3، 6، 9)",
                "يستخدم حقائق الضرب والقسمة والعلاقة بينهما في حلّ جمل مفتوحة",
                "يميّز مفهوم القسمة على أنها تشكيل مجموعات متساوية",
                "يميّز مفهوم القسمة على أنها مشاركة بالتساوي",
                "يوزّع مجموعة من الأشياء إلى مجموعات متساوية ويحدّد عدد المجموعات",
                "يوزّع مجموعة من الأشياء إلى عدد معيّن من المجموعات ويحدّد عدد العناصر في كل مجموعة",
                "يجد ناتج القسمة باستعمال الطرح المتكرر على خط الأعداد",
                "يتعرّف الخاصية التبديلية في الضرب",
                "يتعرّف خاصية العنصر المحايد لعملية الضرب",
                "يتعرّف خاصية الضرب في صفر",
                "يتعرّف خاصية قسمة عدد على واحد",
                "يتعرّف خاصية قسمة عدد (عدا الصفر) على نفسه",
                "يتعرّف خاصية قسمة الصفر على عدد",
                "يتعرّف مفهوم باقي القسمة",
                "يقسم مجموعة من الأشياء إلى مجموعات متساوية، ويجد الباقي"
              ]
            },
            {
              "outcomeAr": "يضرب أعداداً كلية مكوّنة من منزلتين في عدد مكوّن من منزلة واحدة",
              "indicators": [
                "يضرب ذهنياً عدداً كلياً أصغر من 10 في عدد من مضاعفات 10",
                "يجد ناتج ضرب عدد كلي مكوّن من منزلتين في عدد مكوّن من منزلة واحدة مستخدماً خاصية التوزيع",
                "يجد حاصل ضرب عدد كلي مكوّن من منزلتين في عدد مكوّن من منزلة واحدة دون إعادة التجميع",
                "يجد حاصل ضرب عدد كلي مكوّن من منزلتين في عدد مكوّن من منزلة واحدة مع إعادة التجميع",
                "يحل مسائل حياتية على ضرب عدد مكوّن من منزلتين في عدد مكوّن من منزلة واحدة"
              ]
            },
            {
              "outcomeAr": "يقسم أعداداً كلية مكوّنة من منزلتين على عدد مكوّن من منزلة واحدة",
              "indicators": [
                "يقسم عدداً كلياً من منزلتين على عدد مكوّن من منزلة واحدة ضمن حقائق القسمة",
                "يحدّد عناصر خوارزمية القسمة (المقسوم، المقسوم عليه، الناتج، الباقي)",
                "يجد ناتج قسمة عدد من منزلتين على عدد من منزلة واحدة من دون باق باستخدام القسمة الطويلة",
                "يجد ناتج قسمة عدد من منزلتين على عدد من منزلة واحدة مع باق (ناتج من منزلتين)",
                "يجد ناتج قسمة عدد من منزلتين على عدد من منزلة واحدة مع باق (ناتج من منزلة واحدة)",
                "يجد ذهنياً ناتج قسمة عدد من مضاعفات 10 على عدد من منزلة واحدة (من دون باق)",
                "يميّز المواقف التي تتطلب الضرب وتلك التي تتطلب القسمة",
                "يستعمل خطة الخطوات الأربع لحل مسائل حياتية تتطلب القسمة",
                "يفسّر معنى الباقي في المسائل الحياتية"
              ]
            },
            {
              "outcomeAr": "يستخدم استراتيجيات متنوعة لتقدير نواتج العمليات",
              "indicators": [
                "يقدّر حاصل ضرب عدد كلي من منزلتين في عدد من منزلة واحدة مستخدماً التقريب",
                "يقدّر ناتج قسمة عدد كلي من منزلتين على عدد من منزلة واحدة مستعملاً الأعداد المتناغمة"
              ]
            }
          ]
        },
        {
          "nameAr": "الكسور",
          "nameEn": "Fractions",
          "axis": "الأعداد والعد",
          "learningOutcomes": [
            {
              "outcomeAr": "يتعرّف مفهوم الكسر بوصفه جزءاً من أجزاء متساوية",
              "indicators": [
                "يميّز مفهوم الكسر بوصفه جزءاً من كل قُسّم إلى أجزاء متساوية",
                "يميّز مفهوم الكسر بوصفه جزءاً من مجموعة عناصر متماثلة",
                "يقرأ الكسور التي تمثّل جزءاً من كل",
                "يكتب الكسور التي تمثّل جزءاً من كل",
                "يقرأ الكسور التي تمثّل جزءاً من مجموعة عناصر متماثلة",
                "يكتب الكسور التي تمثّل جزءاً من مجموعة عناصر متماثلة",
                "يحدّد البسط والمقام لكسر مُعطى",
                "يدرك أن الكسر m/n يمثّل م جزءاً من أجزاء متساوية",
                "يميّز الكسور المساوية للواحد",
                "يكتب الكسر الدال على الواحد الصحيح من الكل أو من المجموعة",
                "يمثل الكسور وينمذجها مستخدماً شرائط الكسور أو الأشكال",
                "يمثل الكسور على خط الأعداد",
                "يتعرّف مفهوم تكافؤ الكسور",
                "يجد كسوراً متكافئة باستعمال النماذج",
                "يجد كسوراً متكافئة باستعمال خط الأعداد",
                "يجد قيمة كسر وحدة من عدد مكوّن من منزلتين باستخدام القسمة"
              ]
            },
            {
              "outcomeAr": "يميّز الكسور المتكافئة ويمثلها، ويقارن بينها، ويرتبها",
              "indicators": [
                "يقارن بين كسرين باستعمال نماذج الكسور",
                "يقارن بين كسرين باستعمال خط الأعداد",
                "يرتّب ثلاثة كسور تصاعدياً أو تنازلياً باستعمال نماذج الكسور",
                "يرتّب ثلاثة كسور تصاعدياً أو تنازلياً باستعمال خط الأعداد"
              ]
            }
          ]
        }
      ]
    },
    {
      "nameAr": "الأنماط والجبر والاقترانات",
      "nameEn": "Patterns, Algebra & Functions",
      "standards": [
        {
          "nameAr": "أنماط الأعداد والأشكال",
          "nameEn": "Number & Shape Patterns",
          "axis": "الأنماط والأشكال",
          "learningOutcomes": [
            {
              "outcomeAr": "يصف أنماطاً هندسية مُعطاة ويكملها",
              "indicators": [
                "يجد قاعدة نمط هندسي متزايد",
                "يوسع نمطاً هندسياً مُعطى"
              ]
            }
          ]
        },
        {
          "nameAr": "الجملة العددية",
          "nameEn": "Number Sentences",
          "axis": "المقادير والمعادلات والمتباينات",
          "learningOutcomes": [
            {
              "outcomeAr": "يحل مسائل بجملة عددية بسيطة",
              "indicators": [
                "يمثل مسائل حياتية بسيطة بجمل عددية، ويحلّها"
              ]
            }
          ]
        }
      ]
    },
    {
      "nameAr": "الهندسة والقياس",
      "nameEn": "Geometry & Measurement",
      "standards": [
        {
          "nameAr": "المستقيمات والزوايا",
          "nameEn": "Lines & Angles",
          "axis": "الهندسة في بعدين",
          "learningOutcomes": [
            {
              "outcomeAr": "يتعرّف مفاهيم أساسية في المستوى (النقطة، والشعاع، والمستقيم، والقطعة المستقيمة، والزاوية)، ويرسم أشكالاً هندسية",
              "indicators": [
                "يميّز الزاوية، وضلعيها، ورأسها",
                "يميّز المستقيم",
                "يميّز القطعة المستقيمة",
                "يميّز الشعاع",
                "يميّز النقطة",
                "يرسم القطعة المستقيمة والمستقيم والشعاع على شبكة منقّطة",
                "يميّز المستقيمات المتوازية والمتقاطعة والمتعامدة"
              ]
            }
          ]
        },
        {
          "nameAr": "أنواع الزوايا وقياساتها",
          "nameEn": "Types of Angles",
          "axis": "الهندسة في بعدين",
          "learningOutcomes": [
            {
              "outcomeAr": "يصنّف الزوايا، ويرسمها بالمقارنة مع الزاوية القائمة",
              "indicators": [
                "يميّز أنواع الزوايا (الحادة، القائمة، المنفرجة)",
                "يميّز الزوايا الحادة عن طريق أشكالها",
                "يميّز الزوايا المنفرجة عن طريق أشكالها",
                "يصف الزوايا الحادة والقائمة والمنفرجة في أشكال هندسية"
              ]
            }
          ]
        },
        {
          "nameAr": "الأطوال",
          "nameEn": "Length",
          "axis": "القياس",
          "learningOutcomes": [
            {
              "outcomeAr": "يتعرّف وحدات قياس الطول المعيارية (المترية)",
              "indicators": [
                "يتعرّف وحدتيّ الطول: السنتيمتر، والمتر",
                "يتعرّف وحدة الطول: الكيلومتر",
                "يحدّد وحدة الطول المناسبة للقياس في موقف ما"
              ]
            },
            {
              "outcomeAr": "يُجري تحويلات بين وحدات قياس الطول",
              "indicators": [
                "يحوّل بين وحدتي المتر والسنتيمتر (من الأكبر إلى الأصغر)",
                "يحوّل بين وحدتي الكيلومتر والمتر (من الأكبر إلى الأصغر)",
                "يحل مسائل حياتية تتضمن أطوالاً"
              ]
            }
          ]
        },
        {
          "nameAr": "الكتل",
          "nameEn": "Mass",
          "axis": "القياس",
          "learningOutcomes": [
            {
              "outcomeAr": "يتعرّف وحدات قياس الكتل المعيارية (المترية)",
              "indicators": [
                "يتعرّف وحدتيّ قياس الكتلة: الغرام، والكيلوغرام"
              ]
            },
            {
              "outcomeAr": "يُجري تحويلات بين وحدات قياس الكتلة",
              "indicators": [
                "يحوّل بين وحدتي الغرام والكيلوغرام (من الأكبر إلى الأصغر)",
                "يحل مسائل حياتية تتضمن كُتلاً"
              ]
            }
          ]
        },
        {
          "nameAr": "السعات",
          "nameEn": "Capacity",
          "axis": "القياس",
          "learningOutcomes": [
            {
              "outcomeAr": "يتعرّف وحدات قياس السعة المعيارية (المترية)",
              "indicators": [
                "يتعرّف وحدتيّ قياس السعة: اللتر، والمليلتر"
              ]
            },
            {
              "outcomeAr": "يُجري تحويلات بين وحدات قياس السعة",
              "indicators": [
                "يحوّل بين وحدتي اللتر والمليلتر (من الأكبر إلى الأصغر)",
                "يحل مسائل حياتية تتضمن سعات"
              ]
            }
          ]
        },
        {
          "nameAr": "المحيط والمساحة",
          "nameEn": "Perimeter & Area",
          "axis": "القياس",
          "learningOutcomes": [
            {
              "outcomeAr": "يتعرّف مفهوم المحيط، ويحسبه بصورة تقريبية",
              "indicators": [
                "يتعرّف مفهوم المحيط",
                "يجد محيط مضلّع عُلمت أطوال أضلاعه",
                "يجد محيط مضلّع مرسوم على شبكة مربعات",
                "يحل مسائل على محيط المستطيل"
              ]
            }
          ]
        }
      ]
    },
    {
      "nameAr": "تحليل البيانات والاحتمالات",
      "nameEn": "Data Analysis & Probability",
      "standards": [
        {
          "nameAr": "جمع البيانات وتنظيمها وتحليلها وتفسيرها",
          "nameEn": "Collecting, Organizing, Analyzing & Interpreting Data",
          "axis": "التمثيلات البيانية وتحليل البيانات",
          "learningOutcomes": [
            {
              "outcomeAr": "يمثل بيانات في جداول وأعمدة بيانية، ويفسّرها، ويحل مسائل عليها",
              "indicators": [
                "يجمع بيانات حقيقية",
                "يمثل بيانات مستخدماً إشارات العدّ",
                "يمثل بيانات مستخدماً الصور (كل صورة تمثّل نصف عنصر أو عنصر أو عنصرين)",
                "ينظم البيانات في جداول",
                "يفسّر بيانات ممثلة بالصور",
                "يفسّر بيانات ممثلة بجداول الإشارات"
              ]
            }
          ]
        }
      ]
    }
  ]
}
