{
  "kcId": "kc-math-g1-089",
  "kcNameAr": "يقيس الكتلة باستخدام وحدات غير قياسية",
  "domain": "القياس - الكتلة",
  "standard": "يقيس الكتلة باستخدام وحدات غير قياسية",
  "questions": [
    {"id": 11761, "subject": "رياضيات", "lesson": "يقيس الكتلة باستخدام وحدات غير قياسية", "type": "multiple-choice", "questionText": "ما معنى قياس الكتلة بوحدات غير قياسية؟", "options": ["استخدام أشياء مثل المكعبات لمعرفة كم يزن الشيء", "استخدام الكيلوغرام فقط", "لا يمكن قياس الكتلة", "استخدام المسطرة"], "correctAnswer": "استخدام أشياء مثل المكعبات لمعرفة كم يزن الشيء", "points": 10, "hint": "نستخدم أشياء من حولنا كوحدات قياس"},
    {"id": 11762, "subject": "رياضيات", "lesson": "يقيس الكتلة باستخدام وحدات غير قياسية", "type": "multiple-choice", "questionText": "وضعنا تفاحة في كفة ميزان و٦ مكعبات في الكفة الأخرى فتوازنتا. كتلة التفاحة تساوي:", "options": ["٦ مكعبات", "٣ مكعبات", "١٢ مكعباً", "لا نعرف"], "correctAnswer": "٦ مكعبات", "points": 10, "hint": "التوازن يعني كتلة متساوية"},
    {"id": 11763, "subject": "رياضيات", "lesson": "يقيس الكتلة باستخدام وحدات غير قياسية", "type": "multiple-choice", "questionText": "أيّ أداة نستخدم لقياس الكتلة؟", "options": ["ميزان ذو كفتين", "مسطرة", "شريط قياس", "ساعة"], "correctAnswer": "ميزان ذو كفتين", "points": 10, "hint": "الميزان لقياس الكتلة"},
    {"id": 11764, "subject": "رياضيات", "lesson": "يقيس الكتلة باستخدام وحدات غير قياسية", "type": "multiple-choice", "questionText": "كتلة كتاب = ١٠ مكعبات وكتلة ممحاة = ٢ مكعبات. الكتاب أثقل بكم مكعب؟", "options": ["٨ مكعبات", "١٢ مكعباً", "٥ مكعبات", "١٠ مكعبات"], "correctAnswer": "٨ مكعبات", "points": 15, "hint": "١٠ - ٢ = ؟"},
    {"id": 11765, "subject": "رياضيات", "lesson": "يقيس الكتلة باستخدام وحدات غير قياسية", "type": "multiple-choice", "questionText": "أيّ مما يلي وحدة غير قياسية لقياس الكتلة؟", "options": ["مكعبات متساوية", "كيلوغرام", "غرام", "طن"], "correctAnswer": "مكعبات متساوية", "points": 10, "hint": "الكيلوغرام والغرام وحدات قياسية"},
    {"id": 11766, "subject": "رياضيات", "lesson": "يقيس الكتلة باستخدام وحدات غير قياسية", "type": "multiple-choice", "questionText": "وضعنا قلماً في كفة و٣ مكعبات في الكفة الأخرى. الكفة التي فيها القلم نزلت. ماذا نفعل؟", "options": ["نضيف مكعبات حتى يتوازن الميزان", "نزيل مكعبات", "نوقف القياس", "نقلب الميزان"], "correctAnswer": "نضيف مكعبات حتى يتوازن الميزان", "points": 15, "hint": "نضيف مكعبات لموازنة القلم"},
    {"id": 11767, "subject": "رياضيات", "lesson": "يقيس الكتلة باستخدام وحدات غير قياسية", "type": "multiple-choice", "questionText": "لماذا يجب أن تكون المكعبات المستخدمة في القياس متساوية؟", "options": ["لنحصل على قياس دقيق وعادل", "لأنها أجمل", "لا يهم", "لا سبب"], "correctAnswer": "لنحصل على قياس دقيق وعادل", "points": 15, "hint": "وحدات متساوية = قياس دقيق"},
    {"id": 11768, "subject": "رياضيات", "lesson": "يقيس الكتلة باستخدام وحدات غير قياسية", "type": "multiple-choice", "questionText": "كتلة برتقالة = ٨ مكعبات. كتلة تفاحتين = ٨ مكعبات. ماذا نستنتج؟", "options": ["كتلة البرتقالة = كتلة تفاحتين", "البرتقالة أثقل", "التفاحتان أثقل", "لا نعرف"], "correctAnswer": "كتلة البرتقالة = كتلة تفاحتين", "points": 20, "hint": "٨ = ٨"},
    {"id": 11769, "subject": "رياضيات", "lesson": "يقيس الكتلة باستخدام وحدات غير قياسية", "type": "input", "questionText": "توازن الميزان مع دفتر في كفة و٧ مكعبات في الأخرى. كم كتلة الدفتر بالمكعبات؟", "correctAnswer": "٧", "points": 10, "hint": "التوازن = كتلة متساوية"},
    {"id": 11770, "subject": "رياضيات", "lesson": "يقيس الكتلة باستخدام وحدات غير قياسية", "type": "input", "questionText": "كتلة تفاحة = ٤ مكعبات. كتلة ٣ تفاحات متساوية = كم مكعباً؟", "correctAnswer": "١٢", "points": 15, "hint": "٤ × ٣ = ؟"},
    {"id": 11771, "subject": "رياضيات", "lesson": "يقيس الكتلة باستخدام وحدات غير قياسية", "type": "input", "questionText": "كتلة حقيبة = ١٥ مكعباً. أخرجنا منها كتاباً كتلته ٦ مكعبات. كم أصبحت كتلة الحقيبة؟", "correctAnswer": "٩", "points": 15, "hint": "١٥ - ٦ = ؟"},
    {"id": 11772, "subject": "رياضيات", "lesson": "يقيس الكتلة باستخدام وحدات غير قياسية", "type": "input", "questionText": "كتلة كتاب = ١٠ مكعبات. ما نصف كتلته بالمكعبات؟", "correctAnswer": "٥", "points": 15, "hint": "١٠ ÷ ٢ = ؟"},
    {"id": 11773, "subject": "رياضيات", "lesson": "يقيس الكتلة باستخدام وحدات غير قياسية", "type": "input", "questionText": "كتلة قطة = ٢٠ مكعباً. كتلة أرنب = ١٢ مكعباً. كم القطة أثقل؟", "correctAnswer": "٨", "points": 15, "hint": "٢٠ - ١٢ = ؟"},
    {"id": 11774, "subject": "رياضيات", "lesson": "يقيس الكتلة باستخدام وحدات غير قياسية", "type": "reorder", "questionText": "رتّب خطوات قياس كتلة شيء بالمكعبات:", "options": ["ضع الشيء في كفة الميزان", "أضف مكعبات في الكفة الأخرى حتى يتوازن", "عُدّ المكعبات = كتلة الشيء"], "correctAnswer": "ضع الشيء في كفة الميزان,أضف مكعبات في الكفة الأخرى حتى يتوازن,عُدّ المكعبات = كتلة الشيء", "points": 15, "hint": "ضع ثم أضف ثم عُدّ"},
    {"id": 11775, "subject": "رياضيات", "lesson": "يقيس الكتلة باستخدام وحدات غير قياسية", "type": "reorder", "questionText": "رتّب الأشياء حسب كتلتها بالمكعبات من الأخف إلى الأثقل:", "options": ["ممحاة (٢ مكعبات)", "قلم (٤ مكعبات)", "كتاب (٩ مكعبات)"], "correctAnswer": "ممحاة (٢ مكعبات),قلم (٤ مكعبات),كتاب (٩ مكعبات)", "points": 10, "hint": "٢ < ٤ < ٩"},
    {"id": 11776, "subject": "رياضيات", "lesson": "يقيس الكتلة باستخدام وحدات غير قياسية", "type": "reorder", "questionText": "رتّب الكتل من الأثقل إلى الأخف:", "options": ["١٤ مكعباً", "٨ مكعبات", "٣ مكعبات"], "correctAnswer": "١٤ مكعباً,٨ مكعبات,٣ مكعبات", "points": 10, "hint": "من الأكبر إلى الأصغر"},
    {"id": 11777, "subject": "رياضيات", "lesson": "يقيس الكتلة باستخدام وحدات غير قياسية", "type": "matching", "questionText": "طابق كل شيء مع كتلته بالمكعبات:", "pairs": [{"left": "ريشة", "right": "١ مكعب"}, {"left": "تفاحة", "right": "٥ مكعبات"}, {"left": "كتاب", "right": "١٠ مكعبات"}, {"left": "حقيبة", "right": "١٥ مكعباً"}], "correctAnswer": "MATCH_ALL", "points": 15, "hint": "الأشياء الأكبر عادة أثقل"},
    {"id": 11778, "subject": "رياضيات", "lesson": "يقيس الكتلة باستخدام وحدات غير قياسية", "type": "matching", "questionText": "طابق نتيجة الميزان مع معناها:", "pairs": [{"left": "كفة الشيء نزلت", "right": "الشيء أثقل من المكعبات"}, {"left": "كفة المكعبات نزلت", "right": "المكعبات أثقل من الشيء"}, {"left": "الكفتان متوازنتان", "right": "الكتلة متساوية"}, {"left": "نحتاج مكعبات أكثر", "right": "الشيء أثقل من المكعبات الموجودة"}], "correctAnswer": "MATCH_ALL", "points": 20, "hint": "الكفة التي تنزل تحمل الأثقل"}
  ]
}
