{
  "kcId": "kc-math-g1-002",
  "kcNameAr": "يقرأ الأعداد حتى 99 بالكلمات",
  "cards": [
    {
      "id": "fc-002-01",
      "type": "text",
      "front": "اقرأ العدد ١٥ بالكلمات",
      "back": "خمسة عشر",
      "difficulty": 1
    },
    {
      "id": "fc-002-02",
      "type": "text",
      "front": "اقرأ العدد ٣٧ بالكلمات",
      "back": "سبعة وثلاثون",
      "difficulty": 2
    },
    {
      "id": "fc-002-03",
      "type": "text",
      "front": "اقرأ العدد ٤٢ بالكلمات",
      "back": "اثنان وأربعون",
      "difficulty": 2
    },
    {
      "id": "fc-002-04",
      "type": "reverse",
      "front": "ما العدد الذي نقرؤه: واحد وستون؟",
      "back": "٦١",
      "difficulty": 2
    },
    {
      "id": "fc-002-05",
      "type": "text",
      "front": "اقرأ العدد ١١ بالكلمات",
      "back": "أحد عشر",
      "difficulty": 1
    },
    {
      "id": "fc-002-06",
      "type": "text",
      "front": "اقرأ العدد ٩٩ بالكلمات",
      "back": "تسعة وتسعون",
      "difficulty": 3
    },
    {
      "id": "fc-002-07",
      "type": "reverse",
      "front": "ما العدد الذي نقرؤه: ثلاثة وعشرون؟",
      "back": "٢٣",
      "difficulty": 1
    },
    {
      "id": "fc-002-08",
      "type": "concept",
      "front": "كيف نقرأ الأعداد من ٢١ إلى ٩٩؟",
      "back": "نقرأ الآحاد أولاً ثم العشرات. مثال: ٣٤ = أربعة وثلاثون",
      "difficulty": 2
    },
    {
      "id": "fc-002-09",
      "type": "text",
      "front": "اقرأ العدد ٧٨ بالكلمات",
      "back": "ثمانية وسبعون",
      "difficulty": 2
    },
    {
      "id": "fc-002-10",
      "type": "visual",
      "front": "تخيّل بطاقة مكتوب عليها ٥٦. كيف تقرؤها؟",
      "back": "ستة وخمسون",
      "difficulty": 2
    }
  ]
}
